[
    {
        "pool": {
            "name": "2Miners",
            "url": "https://www.2miners.com",
            "fee": 1,
            "type": "PPLNS"
        }
    },
    {
        "coin": "ETHW",
        "servers": [
            {
                "geo": "EU",
                "urls": [
                    "ethw.2miners.com:2020"
                ],
                "ssl_urls": [
                    "ethw.2miners.com:12020"
                ]
            },
            {
                "geo": "RU",
                "urls": [
                    "ethw.2miners.ru:2020"
                ],
                "ssl_urls": [
                    "ethw.2miners.ru:12020"
                ]
            },
            {
                "geo": "US",
                "urls": [
                    "us-ethw.2miners.com:2020"
                ],
                "ssl_urls": [
                    "us-ethw.2miners.com:12020"
                ]
            },
            {
                "geo": "ASIA",
                "urls": [
                    "asia-ethw.2miners.com:2020"
                ],
                "ssl_urls": [
                    "asia-ethw.2miners.com:12020"
                ]
            }
        ],
        "miners": {
            "_prototype": "miners_ethash"
        }
    },
    {
        "coin": "ETC",
        "servers": [
            {
                "geo": "EU",
                "urls": [
                    "etc.2miners.com:1010"
                ],
                "ssl_urls": [
                    "etc.2miners.com:11010"
                ]
            },
            {
                "geo": "RU",
                "urls": [
                    "etc.2miners.ru:1010"
                ],
                "ssl_urls": [
                    "etc.2miners.ru:11010"
                ]
            },
            {
                "geo": "US",
                "urls": [
                    "us-etc.2miners.com:1010"
                ],
                "ssl_urls": [
                    "us-etc.2miners.com:11010"
                ]
            },
            {
                "geo": "ASIA",
                "urls": [
                    "asia-etc.2miners.com:1010"
                ],
                "ssl_urls": [
                    "asia-etc.2miners.com:11010"
                ]
            }
        ],
        "miners": {
            "_prototype": "miners_etchash"
        }
    },
    {
        "coin": "PRL",
        "servers": [
            {
                "geo": "EU",
                "urls": [
                    "prl.2miners.com:1818"
                ],
                "ssl_urls": [
                    "prl.2miners.com:11818"
                ]
            },
            {
                "geo": "RU",
                "urls": [
                    "prl.2miners.ru:1818"
                ],
                "ssl_urls": [
                    "prl.2miners.ru:11818"
                ]
            },
            {
                "geo": "US",
                "urls": [
                    "us-prl.2miners.com:1818"
                ],
                "ssl_urls": [
                    "us-prl.2miners.com:11818"
                ]
            },
            {
                "geo": "ASIA",
                "urls": [
                    "asia-prl.2miners.com:1818"
                ],
                "ssl_urls": [
                    "asia-prl.2miners.com:11818"
                ]
            }
        ],
        "miners": {
            "_prototype": "miners_pearlhash",
            "srbminer": {
                "url": "%URL%",
                "algo": "pearlhash",
                "pass": "x",
                "template": "%WAL%.%WORKER_NAME%"
            }
        }
    },
    {
        "coin": "KAS",
        "servers": [
            {
                "geo": "EU",
                "urls": [
                    "kas.2miners.com:2020"
                ],
                "ssl_urls": [
                    "kas.2miners.com:12020"
                ]
            },
            {
                "geo": "RU",
                "urls": [
                    "kas.2miners.ru:2020"
                ],
                "ssl_urls": [
                    "kas.2miners.ru:12020"
                ]
            },
            {
                "geo": "US",
                "urls": [
                    "us-kas.2miners.com:2020"
                ],
                "ssl_urls": [
                    "us-kas.2miners.com:12020"
                ]
            },
            {
                "geo": "ASIA",
                "urls": [
                    "asia-kas.2miners.com:2020"
                ],
                "ssl_urls": [
                    "asia-kas.2miners.com:12020"
                ]
            }
        ],
        "miners": {
          "_prototype": "miners_kaspa"
        }
    },
    {
        "coin": "NEXA",
        "servers": [
            {
                "geo": "EU",
                "urls": [
                    "nexa.2miners.com:5050"
                ],
                "ssl_urls": [
                    "nexa.2miners.com:15050"
                ]
            },
            {
                "geo": "RU",
                "urls": [
                    "nexa.2miners.ru:5050"
                ],
                "ssl_urls": [
                    "nexa.2miners.ru:15050"
                ]
            },
            {
                "geo": "US",
                "urls": [
                    "us-nexa.2miners.com:5050"
                ],
                "ssl_urls": [
                    "us-nexa.2miners.com:15050"
                ]
            },
            {
                "geo": "ASIA",
                "urls": [
                    "asia-nexa.2miners.com:5050"
                ],
                "ssl_urls": [
                    "asia-nexa.2miners.com:15050"
                ]
            }
        ],
        "miners": {
            "_prototype": "miners_nexapow"
        }
    },
    {
        "coin": "ERG",
        "servers": [
            {
                "geo": "EU",
                "urls": [
                    "erg.2miners.com:8888"
                ],
                "ssl_urls": [
                    "erg.2miners.com:18888"
                ]
            },
            {
                "geo": "RU",
                "urls": [
                    "erg.2miners.ru:8888"
                ],
                "ssl_urls": [
                    "erg.2miners.ru:18888"
                ]
            },
            {
                "geo": "US",
                "urls": [
                    "us-erg.2miners.com:8888"
                ],
                "ssl_urls": [
                    "us-erg.2miners.com:18888"
                ]
            },
            {
                "geo": "ASIA",
                "urls": [
                    "asia-erg.2miners.com:8888"
                ],
                "ssl_urls": [
                    "asia-erg.2miners.com:18888"
                ]
            }
        ],
        "miners": {
		    "_prototype": "miners_autolykos2"
        }
    },
    {
        "coin": "ZEC",
        "servers": [
            {
                "geo": "EU",
                "urls": [
                    "zec.2miners.com:1010"
                ],
                "ssl_urls": [
                    "zec.2miners.com:11010"
                ]
            },
            {
                "geo": "EU HiDIFF",
                "urls": [
                    "zec.2miners.com:1111"
                ],
                "ssl_urls": [
                    "zec.2miners.com:11111"
                ]
            },
            {
                "geo": "RU",
                "urls": [
                    "zec.2miners.ru:1010"
                ],
                "ssl_urls": [
                    "zec.2miners.ru:11010"
                ]
            },
            {
                "geo": "RU HiDIFF",
                "urls": [
                    "zec.2miners.ru:1111"
                ],
                "ssl_urls": [
                    "zec.2miners.ru:11111"
                ]
            },
            {
                "geo": "US",
                "urls": [
                    "us-zec.2miners.com:1010"
                ],
                "ssl_urls": [
                    "us-zec.2miners.com:11010"
                ]
            },
            {
                "geo": "US HiDIFF",
                "urls": [
                    "us-zec.2miners.com:1111"
                ],
                "ssl_urls": [
                    "us-zec.2miners.com:11111"
                ]
            },
            {
                "geo": "ASIA",
                "urls": [
                    "asia-zec.2miners.com:1010"
                ],
                "ssl_urls": [
                    "asia-zec.2miners.com:11010"
                ]
            },
            {
                "geo": "ASIA HiDIFF",
                "urls": [
                    "asia-zec.2miners.com:1111"
                ],
                "ssl_urls": [
                    "asia-zec.2miners.com:11111"
                ]
            }
        ],
        "miners": {
            "dstm": {
                "pass": "x",
                "port": "%URL_PORT%",
                "server": "%URL_HOST%",
                "template": "%WAL%.%WORKER_NAME%"
            },
            "ewbf": {
                "zpass": "x",
                "zport": "%URL_PORT%",
                "zserver": "%URL_HOST%",
                "ztemplate": "%WAL%.%WORKER_NAME%"
            },
            "bminer": {
                "url": "%URL%",
                "pass": "x",
                "template": "%WAL%.%WORKER_NAME%"
            },
            "claymore-z": {
                "zpools_tpl": "POOL: %URL%, WALLET: %WAL%.%WORKER_NAME%"
            },
            "sgminer-gm": {
                "url": "%URL%",
                "algo": "equihash",
                "fork": "gm",
                "pass": "x",
                "template": "%WAL%.%WORKER_NAME%"
            },
            "asicminer": {
                "url": "stratum+tcp://%URL%",
                "template": "%WAL%.%WORKER_NAME%"
            }
        }
    },
    {
        "coin": "BTG",
        "servers": [
            {
                "geo": "EU",
                "urls": [
                    "btg.2miners.com:4040"
                ],
                "ssl_urls": [
                    "btg.2miners.com:14040"
                ]
            },
            {
                "geo": "RU",
                "urls": [
                    "btg.2miners.ru:4040"
                ],
                "ssl_urls": [
                    "btg.2miners.ru:14040"
                ]
            },
            {
                "geo": "US",
                "urls": [
                    "us-btg.2miners.com:4040"
                ],
                "ssl_urls": [
                    "us-btg.2miners.com:14040"
                ]
            },
            {
                "geo": "ASIA",
                "urls": [
                    "asia-btg.2miners.com:4040"
                ],
                "ssl_urls": [
                    "asia-btg.2miners.com:14040"
                ]
            }
        ],
        "miners": {
            "_prototype": "miners_zhash_btg"
        }
    },
    {
        "coin": "GRIN",
        "servers": [
            {
                "geo": "EU",
                "urls": [
                    "grin.2miners.com:3030"
                ],
                "ssl_urls": [
                    "grin.2miners.com:13030"
                ]
            },
            {
                "geo": "RU",
                "urls": [
                    "grin.2miners.ru:3030"
                ],
                "ssl_urls": [
                    "grin.2miners.ru:13030"
                ]
            },
            {
                "geo": "US",
                "urls": [
                    "us-grin.2miners.com:3030"
                ],
                "ssl_urls": [
                    "us-grin.2miners.com:13030"
                ]
            },
            {
                "geo": "ASIA",
                "urls": [
                    "asia-grin.2miners.com:3030"
                ],
                "ssl_urls": [
                    "asia-grin.2miners.com:13030"
                ]
            }
        ],
        "miners": {
            "gminer": {
                "algo": "grin29",
                "port": "%URL_PORT%",
                "server": "%URL_HOST%",
                "template": "%WAL%.%WORKER_NAME%"
            },
            "lolminer": {
                "algo": "GRIN-C32",
                "server": "%URL_HOST%",
                "port": "%URL_PORT%",
                "pass": "x",
                "template": "%WAL%.%WORKER_NAME%"
            },
            "bminer": {
                "algo": "cuckaroo29z",
                "url": "%URL%",
                "pass": "x",
                "template": "%WAL%.%WORKER_NAME%"
            }
        }
    },
    {
        "coin": "ZEPH",
        "servers": [
            {
                "geo": "EU",
                "urls": [
                    "zeph.2miners.com:2222"
                ],
                "ssl_urls": [
                    "zeph.2miners.com:12222"
                ]
            },
            {
                "geo": "EU HiDIFF",
                "urls": [
                    "zeph.2miners.com:3333"
                ],
                "ssl_urls": [
                    "zeph.2miners.com:13333"
                ]
            },
            {
                "geo": "RU",
                "urls": [
                    "zeph.2miners.ru:2222"
                ],
                "ssl_urls": [
                    "zeph.2miners.ru:12222"
                ]
            },
            {
                "geo": "RU HiDIFF",
                "urls": [
                    "zeph.2miners.ru:3333"
                ],
                "ssl_urls": [
                    "zeph.2miners.ru:13333"
                ]
            },
            {
                "geo": "US",
                "urls": [
                    "us-zeph.2miners.com:2222"
                ],
                "ssl_urls": [
                    "us-zeph.2miners.com:12222"
                ]
            },
            {
                "geo": "US HiDIFF",
                "urls": [
                    "us-zeph.2miners.com:3333"
                ],
                "ssl_urls": [
                    "us-zeph.2miners.com:13333"
                ]
            },
            {
                "geo": "ASIA",
                "urls": [
                    "asia-zeph.2miners.com:2222"
                ],
                "ssl_urls": [
                    "asia-zeph.2miners.com:12222"
                ]
            },
            {
                "geo": "ASIA HiDIFF",
                "urls": [
                    "asia-zeph.2miners.com:3333"
                ],
                "ssl_urls": [
                    "asia-zeph.2miners.com:13333"
                ]
            }
        ],
        "miners": {
            "_prototype": "miners_randomx"
        }
    },
    {
        "coin": "RVN",
        "servers": [
            {
                "geo": "EU",
                "urls": [
                    "rvn.2miners.com:6060"
                ],
                "ssl_urls": [
                    "rvn.2miners.com:16060"
                ]
            },
            {
                "geo": "EU HiDIFF",
                "urls": [
                    "rvn.2miners.com:6161"
                ],
                "ssl_urls": [
                    "rvn.2miners.com:16161"
                ]
            },
            {
                "geo": "RU",
                "urls": [
                    "rvn.2miners.ru:6060"
                ],
                "ssl_urls": [
                    "rvn.2miners.ru:16060"
                ]
            },
            {
                "geo": "RU HiDIFF",
                "urls": [
                    "rvn.2miners.ru:6161"
                ],
                "ssl_urls": [
                    "rvn.2miners.ru:16161"
                ]
            },
            {
                "geo": "US",
                "urls": [
                    "us-rvn.2miners.com:6060"
                ],
                "ssl_urls": [
                    "us-rvn.2miners.com:16060"
                ]
            },
            {
                "geo": "US HiDIFF",
                "urls": [
                    "us-rvn.2miners.com:6161"
                ],
                "ssl_urls": [
                    "us-rvn.2miners.com:16161"
                ]
            },
            {
                "geo": "ASIA",
                "urls": [
                    "asia-rvn.2miners.com:6060"
                ],
                "ssl_urls": [
                    "asia-rvn.2miners.com:16060"
                ]
            },
            {
                "geo": "ASIA HiDIFF",
                "urls": [
                    "asia-rvn.2miners.com:6161"
                ],
                "ssl_urls": [
                    "asia-rvn.2miners.com:16161"
                ]
            }
        ],
        "miners": {
            "_prototype": "miners_kawpow"
        }
    },
    {
        "coin": "XNA",
        "servers": [
            {
                "geo": "EU",
                "urls": [
                    "xna.2miners.com:6060"
                ],
                "ssl_urls": [
                    "xna.2miners.com:16060"
                ]
            },
            {
                "geo": "EU HiDIFF",
                "urls": [
                    "xna.2miners.com:6161"
                ],
                "ssl_urls": [
                    "xna.2miners.com:16161"
                ]
            },
            {
                "geo": "RU",
                "urls": [
                    "xna.2miners.ru:6060"
                ],
                "ssl_urls": [
                    "xna.2miners.ru:16060"
                ]
            },
            {
                "geo": "RU HiDIFF",
                "urls": [
                    "xna.2miners.ru:6161"
                ],
                "ssl_urls": [
                    "xna.2miners.ru:16161"
                ]
            },
            {
                "geo": "US",
                "urls": [
                    "us-xna.2miners.com:6060"
                ],
                "ssl_urls": [
                    "us-xna.2miners.com:16060"
                ]
            },
            {
                "geo": "US HiDIFF",
                "urls": [
                    "us-xna.2miners.com:6161"
                ],
                "ssl_urls": [
                    "us-xna.2miners.com:16161"
                ]
            },
            {
                "geo": "ASIA",
                "urls": [
                    "asia-xna.2miners.com:6060"
                ],
                "ssl_urls": [
                    "asia-xna.2miners.com:16060"
                ]
            },
            {
                "geo": "ASIA HiDIFF",
                "urls": [
                    "asia-xna.2miners.com:6161"
                ],
                "ssl_urls": [
                    "asia-xna.2miners.com:16161"
                ]
            }
        ],
        "miners": {
            "_prototype": "miners_kawpow"
        }
    },
    {
        "coin": "AE",
        "servers": [
            {
                "geo": "EU",
                "urls": [
                    "ae.2miners.com:4040"
                ],
                "ssl_urls": [
                    "ae.2miners.com:14040"
                ]
            },
            {
                "geo": "EU HiDIFF",
                "urls": [
                    "ae.2miners.com:4242"
                ],
                "ssl_urls": [
                    "ae.2miners.com:14242"
                ]
            },
            {
                "geo": "RU",
                "urls": [
                    "ae.2miners.ru:4040"
                ],
                "ssl_urls": [
                    "ae.2miners.ru:14040"
                ]
            },
            {
                "geo": "RU HiDIFF",
                "urls": [
                    "ae.2miners.ru:4242"
                ],
                "ssl_urls": [
                    "ae.2miners.ru:14242"
                ]
            },
            {
                "geo": "US",
                "urls": [
                    "us-ae.2miners.com:4040"
                ],
                "ssl_urls": [
                    "us-ae.2miners.com:14040"
                ]
            },
            {
                "geo": "US HiDIFF",
                "urls": [
                    "us-ae.2miners.com:4242"
                ],
                "ssl_urls": [
                    "us-ae.2miners.com:14242"
                ]
            },
            {
                "geo": "ASIA",
                "urls": [
                    "asia-ae.2miners.com:4040"
                ],
                "ssl_urls": [
                    "asia-ae.2miners.com:14040"
                ]
            },
            {
                "geo": "ASIA HiDIFF",
                "urls": [
                    "asia-ae.2miners.com:4242"
                ],
                "ssl_urls": [
                    "asia-ae.2miners.com:14242"
                ]
            }
        ],
        "miners": {
            "bminer": {
                "algo": "aeternity",
                "template": "%WAL%.%WORKER_NAME%",
                "url": "%URL%"
            },
            "gminer": {
                "algo": "aeternity",
                "port": "%URL_PORT%",
                "server": "%URL_HOST%",
                "template": "%WAL%.%WORKER_NAME%"
            },
            "cryptodredge": {
                "url": "%URL%",
                "pass": "x",
                "template": "%WAL%.%WORKER_NAME%",
                "algo": "aeternity"
            }
        }
    },
    {
        "coin": "BEAM",
        "servers": [
            {
                "geo": "EU",
                "ssl_urls": [
                    "beam.2miners.com:5252"
                ]
            },
            {
                "geo": "EU HiDIFF",
                "ssl_urls": [
                    "beam.2miners.com:5353"
                ]
            },
            {
                "geo": "RU",
                "ssl_urls": [
                    "beam.2miners.ru:5252"
                ]
            },
            {
                "geo": "RU HiDIFF",
                "ssl_urls": [
                    "beam.2miners.ru:5353"
                ]
            },
            {
                "geo": "US",
                "ssl_urls": [
                    "us-beam.2miners.com:5252"
                ]
            },
            {
                "geo": "US HiDIFF",
                "ssl_urls": [
                    "us-beam.2miners.com:5353"
                ]
            },
            {
                "geo": "ASIA",
                "ssl_urls": [
                    "asia-beam.2miners.com:5252"
                ]
            },
            {
                "geo": "ASIA HiDIFF",
                "ssl_urls": [
                    "asia-beam.2miners.com:5353"
                ]
            }
        ],
        "miners": {
            "_prototype": "miners_beamhash"
        }
    },
    {
        "coin": "CKB",
        "servers": [
            {
                "geo": "EU",
                "urls": [
                    "ckb.2miners.com:6464"
                ],
                "ssl_urls": [
                    "ckb.2miners.com:16464"
                ]
            },
            {
                "geo": "EU HiDIFF",
                "urls": [
                    "ckb.2miners.com:6565"
                ],
                "ssl_urls": [
                    "ckb.2miners.com:16565"
                ]
            },
            {
                "geo": "RU",
                "urls": [
                    "ckb.2miners.ru:6464"
                ],
                "ssl_urls": [
                    "ckb.2miners.ru:16464"
                ]
            },
            {
                "geo": "RU HiDIFF",
                "urls": [
                    "ckb.2miners.ru:6565"
                ],
                "ssl_urls": [
                    "ckb.2miners.ru:16565"
                ]
            },
            {
                "geo": "US",
                "urls": [
                    "us-ckb.2miners.com:6464"
                ],
                "ssl_urls": [
                    "us-ckb.2miners.com:16464"
                ]
            },
            {
                "geo": "US HiDIFF",
                "urls": [
                    "us-ckb.2miners.com:6565"
                ],
                "ssl_urls": [
                    "us-ckb.2miners.com:16565"
                ]
            },
            {
                "geo": "ASIA",
                "urls": [
                    "asia-ckb.2miners.com:6464"
                ],
                "ssl_urls": [
                    "asia-ckb.2miners.com:16464"
                ]
            },
            {
                "geo": "ASIA HiDIFF",
                "urls": [
                    "asia-ckb.2miners.com:6565"
                ],
                "ssl_urls": [
                    "asia-ckb.2miners.com:16565"
                ]
            }
        ],
        "miners": {
            "gminer": {
                "server": "%URL_HOST%",
                "port": "%URL_PORT%",
                "template": "%WAL%.%WORKER_NAME%",
                "algo": "eaglesong"
            },
            "nbminer": {
                "url": "%URL%",
                "template": "%WAL%.%WORKER_NAME%",
                "algo": "eaglesong"
            },
            "bminer": {
                "url": "%URL%",
                "template": "%WAL%.%WORKER_NAME%",
                "pass": "x",
                "algo": "ckb"
            },
            "smine": {
                "url": "%URL%",
                "template": "%WAL%.%WORKER_NAME%",
                "pass": "x"
            }
        }
    },
    {
        "coin": "BCH",
        "servers": [
            {
                "geo": "EU",
                "urls": [
                    "bch.2miners.com:7373"
                ],
                "ssl_urls": [
                    "bch.2miners.com:17373"
                ]
            },
            {
                "geo": "RU",
                "urls": [
                    "bch.2miners.ru:7373"
                ],
                "ssl_urls": [
                    "bch.2miners.ru:17373"
                ]
            },
            {
                "geo": "US",
                "urls": [
                    "us-bch.2miners.com:7373"
                ],
                "ssl_urls": [
                    "us-bch.2miners.com:17373"
                ]
            },
            {
                "geo": "ASIA",
                "urls": [
                    "asia-bch.2miners.com:7373"
                ],
                "ssl_urls": [
                    "asia-bch.2miners.com:17373"
                ]
            }
        ],
        "miners": {
            "asicminer": {
                "url": "stratum+tcp://%URL%",
                "template": "%WAL%.%WORKER_NAME%"
            }
        }
    },
    {
        "coin": "QUAI",
        "servers": [
            {
                "geo": "EU",
                "urls": [
                    "quaikawpow.2miners.com:4545"
                ],
                "ssl_urls": [
                    "quaikawpow.2miners.com:14545"
                ]
            },
            {
                "geo": "EU HiDIFF",
                "urls": [
                    "quaikawpow.2miners.com:4646"
                ],
                "ssl_urls": [
                    "quaikawpow.2miners.com:14646"
                ]
            },
            {
                "geo": "RU",
                "urls": [
                    "quaikawpow.2miners.ru:4545"
                ],
                "ssl_urls": [
                    "quaikawpow.2miners.ru:14545"
                ]
            },
            {
                "geo": "RU HiDIFF",
                "urls": [
                    "quaikawpow.2miners.ru:4646"
                ],
                "ssl_urls": [
                    "quaikawpow.2miners.ru:14646"
                ]
            },
            {
                "geo": "US",
                "urls": [
                    "us-quaikawpow.2miners.com:4545"
                ],
                "ssl_urls": [
                    "us-quaikawpow.2miners.com:14545"
                ]
            },
            {
                "geo": "US HiDIFF",
                "urls": [
                    "us-quaikawpow.2miners.com:4646"
                ],
                "ssl_urls": [
                    "us-quaikawpow.2miners.com:14646"
                ]
            },
            {
                "geo": "ASIA",
                "urls": [
                    "asia-quaikawpow.2miners.com:4545"
                ],
                "ssl_urls": [
                    "asia-quaikawpow.2miners.com:14545"
                ]
            },
            {
                "geo": "ASIA HiDIFF",
                "urls": [
                    "asia-quaikawpow.2miners.com:4646"
                ],
                "ssl_urls": [
                    "asia-quaikawpow.2miners.com:14646"
                ]
            }
        ],
        "miners": {
            "_prototype": "miners_kawpow"
        }
    },
    {
        "coin": "QUAI-sha256",
        "servers": [
            {
                "geo": "EU",
                "urls": [
                    "quaisha.2miners.com:8080"
                ],
                "ssl_urls": [
                    "quaisha.2miners.com:18080"
                ]
            },
            {
                "geo": "EU MedDIFF",
                "urls": [
                    "quaisha.2miners.com:8181"
                ],
                "ssl_urls": [
                    "quaisha.2miners.com:18181"
                ]
            },
            {
                "geo": "EU HiDIFF",
                "urls": [
                    "quaisha.2miners.com:8282"
                ],
                "ssl_urls": [
                    "quaisha.2miners.com:18282"
                ]
            },
            {
                "geo": "RU",
                "urls": [
                    "quaisha.2miners.ru:8080"
                ],
                "ssl_urls": [
                    "quaisha.2miners.ru:18080"
                ]
            },
            {
                "geo": "RU MedDIFF",
                "urls": [
                    "quaisha.2miners.ru:8181"
                ],
                "ssl_urls": [
                    "quaisha.2miners.ru:18181"
                ]
            },
            {
                "geo": "RU HiDIFF",
                "urls": [
                    "quaisha.2miners.ru:8282"
                ],
                "ssl_urls": [
                    "quaisha.2miners.ru:18282"
                ]
            },
            {
                "geo": "US",
                "urls": [
                    "us-quaisha.2miners.com:8080"
                ],
                "ssl_urls": [
                    "us-quaisha.2miners.com:18080"
                ]
            },
            {
                "geo": "US MedDIFF",
                "urls": [
                    "us-quaisha.2miners.com:8181"
                ],
                "ssl_urls": [
                    "us-quaisha.2miners.com:18181"
                ]
            },
            {
                "geo": "US HiDIFF",
                "urls": [
                    "us-quaisha.2miners.com:8282"
                ],
                "ssl_urls": [
                    "us-quaisha.2miners.com:18282"
                ]
            },
            {
                "geo": "ASIA",
                "urls": [
                    "asia-quaisha.2miners.com:8080"
                ],
                "ssl_urls": [
                    "asia-quaisha.2miners.com:18080"
                ]
            },
            {
                "geo": "ASIA MedDIFF",
                "urls": [
                    "asia-quaisha.2miners.com:8181"
                ],
                "ssl_urls": [
                    "asia-quaisha.2miners.com:18181"
                ]
            },
            {
                "geo": "ASIA HiDIFF",
                "urls": [
                    "asia-quaisha.2miners.com:8282"
                ],
                "ssl_urls": [
                    "asia-quaisha.2miners.com:18282"
                ]
            }
        ],
        "miners": {
            "asicminer": {
                "url": "stratum+tcp://%URL%",
                "template": "%WAL%.%WORKER_NAME%"
            }
        }
    }
]
