[
    {
        "pool": {
            "name": "Aiwakuang",
            "url": "https://wow.aiwakuang.cn",
            "fee": 1,
            "type": "PPLNS"
        }
    },
    {
        "coin": "WOW",
        "servers": [
            {
                "geo": "China",
                "urls": [
                    "aiwakuang.cn:4555"
                ]
            }
        ],
        "miners": {
            "xmrig": {
                "url": "%URL%",
                "pass": "x",
                "template": "%WAL%",
                "user_config": "\"algo\": \"cryptonight/r\""
            },
            "xmrig-amd": {
                "url": "%URL%",
                "pass": "x",
                "template": "%WAL%",
                "user_config": "\"algo\": \"cryptonight/r\""
            },
            "xmrig-nvidia": {
                "url": "%URL%",
                "pass": "x",
                "template": "%WAL%",
                "user_config": "\"algo\": \"cryptonight/r\""
            }
        }
    }
]
