[

{
		"coin": "BTCZ",
		"servers": [{
				"geo": "EU",
				"urls": [
					"mine-btcz-euro.equipool.1ds.us:50063"
				]
			},
			{
				"geo": "US",
				"urls": [
					"mine-btcz-na.equipool.1ds.us:50063"
				]
			},
			{
				"geo": "Asia",
				"urls": [
					"mine-btcz-asia.equipool.1ds.us:50063"
				]
			}
		],

		"miners": {
				"ewbf": {
				"algo":"144_5",
				"fork":"zhash",
				"zpass": "x",
				"zport": "%URL_PORT%",
				"zserver": "%URL_HOST%",
				"ztemplate": "%WAL%.%WORKER_NAME%",
				 "user_config": "pers BitcoinZ"
			}
		}
	},


	{
		"coin": "ZEL",
		"servers": [{
				"geo": "EU",
				"urls": [
					"mine-zel-euro.equipool.1ds.us:50053"
				]
			},
			{
				"geo": "US",
				"urls": [
					"mine-zel-na.equipool.1ds.us:50053"
				]
			},
			{
				"geo": "Asia",
				"urls": [
					"mine-zel-asia.equipool.1ds.us:50053"
				]
			}
		],

		"miners": {
				"ewbf": {
				"algo":"144_5",
				"fork":"zhash",
				"zpass": "x",
				"zport": "%URL_PORT%",
				"zserver": "%URL_HOST%",
				"ztemplate": "%WAL%.%WORKER_NAME%",
				"user_config": "pers ZelProof"
			}
		}
	}

]
