[
    {
        "pool": {
            "name": "NeuroPool",
            "url": "https://dynex.neuropool.net",
            "fee": 0.9,
            "type": "PROP"
        }
    },

    {
        "coin": "DNX",
        "servers": [
            {
                "geo": "EU/Frankfurt",
                "urls": [
                    "dnx.eu.neuropool.net:19333"
                ],
                "ssl_urls": [
                    "dnx.eu.neuropool.net:19343"
                ]
            },
            {
                "geo": "US/Chicago",
                "urls": [
                    "dnx.us.neuropool.net:19333"
                ],
                  "ssl_urls": [
                    "dnx.us.neuropool.net:19343"
                ]
            },
            {
                "geo": "AS2/Hong Kong",
                "urls": [
                    "dnx.as2.neuropool.net:19333"
                ],
                  "ssl_urls": [
                    "dnx.as2.neuropool.net:19343"
                ]
            },
            {
                "geo": "AU/Melbourne",
                "urls": [
                    "dnx.au.neuropool.net:19333"
                ],
                  "ssl_urls": [
                    "dnx.au.neuropool.net:19343"
                ]
            }
        ],
        "miners": {
            "_prototype": "miners_dynexsolve",
            "onezerominer": {
                "user_config": ""
            }
        }
    }

]
