[
  {
    "pool": {
      "name": "PMP_Mining-Pool",
      "url": "https://www.pmpmining.com",
      "type": "PPLNS"
    }
  },
  {
    "coin": "BBC",
    "servers": [
      {
        "geo": "Australia (Sydney)",
        "urls": ["au.pmpmining.com:5037"]
      },
      {
        "geo": "Sth America (Brasil / Sao Paulo)",
        "urls": ["br.pmpmining.com:5037"]
      },
      {
        "geo": "Europe (Germany / Dusseldorf)",
        "urls": ["de.pmpmining.com:5037"]
      },
      {
        "geo": "USA (South Carolina)",
        "urls": ["us-east.pmpmining.com:5037"]
      },
      {
        "geo": "USA (St Louis)",
        "urls": ["us-central.pmpmining.com:5037"]
      },
      {
        "geo": "ASIA (Singapore)",
        "urls": ["sg.pmpmining.com:5037"]
      }
    ],
    "miners": {
      "_prototype": "miners_ghostrider"
    }
  },
  {
    "coin": "BTC",
    "servers": [
      {
        "geo": "USA (South Carolina) Nicehash/MRR",
        "urls": ["btc-us-east.pmpmining.com:4008"]
      },
      {
        "geo": "USA (South Carolina) Hi Diff",
        "urls": ["btc-us-east.pmpmining.com:4010"]
      }
    ],
    "miners": {
      "asicminer": {
        "url": "stratum+tcp://%URL%",
        "template": "%WAL%.%WORKER_NAME%"
      }
    }
  },
  {
    "coin": "BTG",
    "servers": [
      {
        "geo": "Australia (Sydney) Lo Diff",
        "urls": ["au.pmpmining.com:3052"]
      },
      {
        "geo": "Australia (Sydney) Hi Diff",
        "urls": ["au.pmpmining.com:3053"]
      },
      {
        "geo": "Sth America (Brasil / Sao Paulo) Lo Diff",
        "urls": ["br.pmpmining.com:3052"]
      },
      {
        "geo": "Sth America (Brasil / Sao Paulo) Hi Diff",
        "urls": ["br.pmpmining.com:3053"]
      },
      {
        "geo": "Europe (Germany / Dusseldorf) Lo Diff",
        "urls": ["de.pmpmining.com:3052"]
      },
      {
        "geo": "Europe (Germany / Dusseldorf) Hi Diff",
        "urls": ["de.pmpmining.com:3053"]
      },
      {
        "geo": "USA (South Carolina) Lo Diff",
        "urls": ["us-east.pmpmining.com:3052"]
      },
      {
        "geo": "USA (South Carolina) Hi Diff",
        "urls": ["us-east.pmpmining.com:3053"]
      },
      {
        "geo": "USA (St Louis) Lo Diff",
        "urls": ["us-central.pmpmining.com:3052"]
      },
      {
        "geo": "USA (St Louis) Hi Diff",
        "urls": ["us-central.pmpmining.com:3053"]
      },
      {
        "geo": "ASIA (Singapore) Lo Diff",
        "urls": ["sg.pmpmining.com:3052"]
      },
      {
        "geo": "ASIA (Singapore) Hi Diff",
        "urls": ["sg.pmpmining.com:3053"]
      }
    ],
    "miners": {
      "_prototype": "miners_zhash_btg"
    }
  },
  {
    "coin": "BTRM",
    "servers": [
      {
        "geo": "Australia (Sydney)",
        "urls": ["au.pmpmining.com:5015"]
      },
      {
        "geo": "Sth America (Brasil / Sao Paulo)",
        "urls": ["br.pmpmining.com:5015"]
      },
      {
        "geo": "Europe (Germany / Dusseldorf)",
        "urls": ["de.pmpmining.com:5015"]
      },
      {
        "geo": "USA (South Carolina)",
        "urls": ["us-east.pmpmining.com:5015"]
      },
      {
        "geo": "USA (St Louis)",
        "urls": ["us-central.pmpmining.com:5015"]
      },
      {
        "geo": "ASIA (Singapore)",
        "urls": ["sg.pmpmining.com:5015"]
      }
    ],
    "miners": {
      "_prototype": "miners_ghostrider"
    }
  },
  {
    "coin": "CLORE",
    "servers": [
      {
        "geo": "Australia (Sydney)",
        "urls": ["au.pmpmining.com:6455"]
      },
      {
        "geo": "Sth America (Brasil / Sao Paulo)",
        "urls": ["br.pmpmining.com:6455"]
      },
      {
        "geo": "Europe (Germany / Dusseldorf)",
        "urls": ["de.pmpmining.com:6455"]
      },
      {
        "geo": "USA (South Carolina)",
        "urls": ["us-east.pmpmining.com:6455"]
      },
      {
        "geo": "USA (St Louis)",
        "urls": ["us-central.pmpmining.com:6455"]
      },
      {
        "geo": "ASIA (Singapore)",
        "urls": ["sg.pmpmining.com:6455"]
      }
    ],
    "miners": {
      "_prototype": "miners_kawpow"
    }
  },
  {
    "coin": "DGB-Sha256d",
    "servers": [
      {
        "geo": "Australia (Sydney) Lo Diff",
        "urls": ["au.pmpmining.com:4010"]
      },
      {
        "geo": "Australia (Sydney) Hi Diff",
        "urls": ["au.pmpmining.com:4008"]
      },
      {
        "geo": "Sth America (Brasil / Sao Paulo) Lo Diff",
        "urls": ["br.pmpmining.com:4010"]
      },
      {
        "geo": "Sth America (Brasil / Sao Paulo) Hi Diff",
        "urls": ["br.pmpmining.com:4008"]
      },
      {
        "geo": "Europe (Germany / Dusseldorf) Lo Diff",
        "urls": ["de.pmpmining.com:4010"]
      },
      {
        "geo": "Europe (Germany / Dusseldorf) Hi Diff",
        "urls": ["de.pmpmining.com:4008"]
      },
      {
        "geo": "USA (South Carolina) Lo Diff",
        "urls": ["us-east.pmpmining.com:4010"]
      },
      {
        "geo": "USA (South Carolina) Hi Diff",
        "urls": ["us-east.pmpmining.com:4008"]
      },
      {
        "geo": "USA (St Louis) Lo Diff",
        "urls": ["us-central.pmpmining.com:4010"]
      },
      {
        "geo": "USA (St Louis) Hi Diff",
        "urls": ["us-central.pmpmining.com:4008"]
      },
      {
        "geo": "ASIA (Singapore) Lo Diff",
        "urls": ["sg.pmpmining.com:4010"]
      },
      {
        "geo": "ASIA (Singapore) Hi Diff",
        "urls": ["sg.pmpmining.com:4008"]
      }
    ],
    "miners": {
      "asicminer": {
        "url": "stratum+tcp://%URL%",
        "template": "%WAL%"
      }
    }
  },
  {
    "coin": "FNNC",
    "servers": [
      {
        "geo": "Australia (Sydney)",
        "urls": ["au.pmpmining.com:5080"]
      },
      {
        "geo": "Sth America (Brasil / Sao Paulo)",
        "urls": ["br.pmpmining.com:5080"]
      },
      {
        "geo": "Europe (Germany / Dusseldorf)",
        "urls": ["de.pmpmining.com:5080"]
      },
      {
        "geo": "USA (South Carolina)",
        "urls": ["us-east.pmpmining.com:5080"]
      },
      {
        "geo": "USA (St Louis)",
        "urls": ["us-central.pmpmining.com:5080"]
      },
      {
        "geo": "ASIA (Singapore)",
        "urls": ["sg.pmpmining.com:5080"]
      }
    ],
    "miners": {
      "srbminer": {
        "url": "%URL%",
        "algo": "yescryptr16",
        "pass": "x",
        "worker": "%WORKER_NAME%",
        "template": "%WAL%",
        "user_config": "--disable-cpu"
      }
    }
  },
  {
    "coin": "GOLD",
    "servers": [
      {
        "geo": "Australia (Sydney) GPU",
        "urls": ["au.pmpmining.com:5076"]
      },
      {
        "geo": "Sth America (Brasil / Sao Paulo) GPU",
        "urls": ["br.pmpmining.com:5076"]
      },
      {
        "geo": "Europe (Germany / Dusseldorf) GPU",
        "urls": ["de.pmpmining.com:5076"]
      },
      {
        "geo": "USA (South Carolina) GPU",
        "urls": ["us-east.pmpmining.com:5076"]
      },
      {
        "geo": "USA (St Louis) GPU",
        "urls": ["us-central.pmpmining.com:5076"]
      },
      {
        "geo": "ASIA (Singapore) GPU",
        "urls": ["sg.pmpmining.com:5076"]
      },
      {
        "geo": "Australia (Sydney) CPU",
        "urls": ["au.pmpmining.com:5078"]
      },
      {
        "geo": "Sth America (Brasil / Sao Paulo) CPU",
        "urls": ["br.pmpmining.com:5078"]
      },
      {
        "geo": "Europe (Germany / Dusseldorf) CPU",
        "urls": ["de.pmpmining.com:5078"]
      },
      {
        "geo": "USA (South Carolina) CPU",
        "urls": ["us-east.pmpmining.com:5078"]
      },
      {
        "geo": "USA (St Louis) CPU",
        "urls": ["us-central.pmpmining.com:5078"]
      },
      {
        "geo": "ASIA (Singapore) CPU",
        "urls": ["sg.pmpmining.com:5078"]
      }
    ],
    "miners": {
      "srbminer": {
        "url": "%URL%",
        "algo": "yescryptr16",
        "pass": "x",
        "worker": "%WORKER_NAME%",
        "template": "%WAL%",
        "user_config": "--disable-cpu"
      }
    }
  },
  {
    "coin": "KCN",
    "servers": [
      {
        "geo": "Australia (Sydney)",
        "urls": ["au.pmpmining.com:9197"]
      },
      {
        "geo": "Sth America (Brasil / Sao Paulo)",
        "urls": ["br.pmpmining.com:9197"]
      },
      {
        "geo": "Europe (Germany / Dusseldorf)",
        "urls": ["de.pmpmining.com:9197"]
      },
      {
        "geo": "USA (South Carolina)",
        "urls": ["us-east.pmpmining.com:9197"]
      },
      {
        "geo": "USA (St Louis)",
        "urls": ["us-central.pmpmining.com:9197"]
      },
      {
        "geo": "ASIA (Singapore)",
        "urls": ["sg.pmpmining.com:9197"]
      }
    ],
    "miners": {
      "ccminer": {
        "ccurl": "stratum+tcp://%URL%",
        "ccuser": "%WAL%",
        "ccalgo": "sha3d",
        "ccpass": "x",
        "fork": "bsha3"
      },
      "srbminer": {
        "url": "%URL%",
        "algo": "sha3d",
        "pass": "x",
        "template": "%WAL%.%WORKER_NAME%"
      },
      "bzminer": {
        "url": "%URL%",
        "algo": "kylacoin",
        "pass": "x",
        "template": "%WAL%.%WORKER_NAME%"
      }
    }
  },
  {
    "coin": "LTC",
    "servers": [
      {
        "geo": "Australia (Sydney)",
        "urls": ["au.pmpmining.com:5055"]
      },
      {
        "geo": "Sth America (Brasil / Sao Paulo)",
        "urls": ["br.pmpmining.com:5055"]
      },
      {
        "geo": "Europe (Germany / Dusseldorf)",
        "urls": ["de.pmpmining.com:5055"]
      },
      {
        "geo": "USA (South Carolina)",
        "urls": ["us-east.pmpmining.com:5055"]
      },
      {
        "geo": "USA (St Louis)",
        "urls": ["us-central.pmpmining.com:5055"]
      },
      {
        "geo": "ASIA (Singapore)",
        "urls": ["sg.pmpmining.com:5055"]
      }
    ],
    "miners": {
      "asicminer": {
        "url": "stratum+tcp://%URL%",
        "template": "%WAL%.%WORKER_NAME%"
      }
    }
  },
  {
    "coin": "MAXE",
    "servers": [
      {
        "geo": "Australia (Sydney)",
        "urls": ["au.pmpmining.com:17057"]
      },
      {
        "geo": "Sth America (Brasil / Sao Paulo)",
        "urls": ["br.pmpmining.com:17057"]
      },
      {
        "geo": "Europe (Germany / Dusseldorf)",
        "urls": ["de.pmpmining.com:17057"]
      },
      {
        "geo": "USA (South Carolina)",
        "urls": ["us-east.pmpmining.com:17057"]
      },
      {
        "geo": "USA (St Louis)",
        "urls": ["us-central.pmpmining.com:17057"]
      },
      {
        "geo": "ASIA (Singapore)",
        "urls": ["sg.pmpmining.com:17057"]
      }
    ],
    "miners": {
      "_prototype": "miners_ghostrider"
    }
  },
  {
    "coin": "MAZA-Sha256d",
    "servers": [
      {
        "geo": "Australia (Sydney) Lo Diff",
        "urls": ["au.pmpmining.com:3084"]
      },
      {
        "geo": "Australia (Sydney) Hi Diff",
        "urls": ["au.pmpmining.com:3085"]
      },
      {
        "geo": "Sth America (Brasil / Sao Paulo) Lo Diff",
        "urls": ["br.pmpmining.com:3084"]
      },
      {
        "geo": "Sth America (Brasil / Sao Paulo) Hi Diff",
        "urls": ["br.pmpmining.com:3085"]
      },
      {
        "geo": "Europe (Germany / Dusseldorf) Lo Diff",
        "urls": ["de.pmpmining.com:3084"]
      },
      {
        "geo": "Europe (Germany / Dusseldorf) Hi Diff",
        "urls": ["de.pmpmining.com:3085"]
      },
      {
        "geo": "USA (South Carolina) Lo Diff",
        "urls": ["us-east.pmpmining.com:3084"]
      },
      {
        "geo": "USA (South Carolina) Hi Diff",
        "urls": ["us-east.pmpmining.com:3085"]
      },
      {
        "geo": "USA (St Louis) Lo Diff",
        "urls": ["us-central.pmpmining.com:3084"]
      },
      {
        "geo": "USA (St Louis) Hi Diff",
        "urls": ["us-central.pmpmining.com:3085"]
      },
      {
        "geo": "ASIA (Singapore) Lo Diff",
        "urls": ["sg.pmpmining.com:3084"]
      },
      {
        "geo": "ASIA (Singapore) Hi Diff",
        "urls": ["sg.pmpmining.com:3085"]
      }
    ],
    "miners": {
      "asicminer": {
        "url": "stratum+tcp://%URL%",
        "template": "%WAL%"
      }
    }
  },
  {
    "coin": "MEWC",
    "servers": [
      {
        "geo": "Australia (Sydney)",
        "urls": ["au.pmpmining.com:9086"]
      },
      {
        "geo": "Sth America (Brasil / Sao Paulo)",
        "urls": ["br.pmpmining.com:9086"]
      },
      {
        "geo": "Europe (Germany / Dusseldorf)",
        "urls": ["de.pmpmining.com:9086"]
      },
      {
        "geo": "USA (South Carolina)",
        "urls": ["us-east.pmpmining.com:9086"]
      },
      {
        "geo": "USA (St Louis)",
        "urls": ["us-central.pmpmining.com:9086"]
      },
      {
        "geo": "ASIA (Singapore)",
        "urls": ["sg.pmpmining.com:9086"]
      }
    ],
    "miners": {
      "_prototype": "miners_kawpow"
    }
  },
  {
    "coin": "NOVO",
    "servers": [
      {
        "geo": "Australia (Sydney) Lo Diff",
        "urls": ["au.pmpmining.com:5084"]
      },
      {
        "geo": "Australia (Sydney) Hi Diff",
        "urls": ["au.pmpmining.com:5085"]
      },
      {
        "geo": "Sth America (Brasil / Sao Paulo) Lo Diff",
        "urls": ["br.pmpmining.com:5084"]
      },
      {
        "geo": "Sth America (Brasil / Sao Paulo) Hi Diff",
        "urls": ["br.pmpmining.com:5085"]
      },
      {
        "geo": "Europe (Germany / Dusseldorf) Lo Diff",
        "urls": ["de.pmpmining.com:5084"]
      },
      {
        "geo": "Europe (Germany / Dusseldorf) Hi Diff",
        "urls": ["de.pmpmining.com:5085"]
      },
      {
        "geo": "USA (South Carolina) Lo Diff",
        "urls": ["us-east.pmpmining.com:5084"]
      },
      {
        "geo": "USA (South Carolina) Hi Diff",
        "urls": ["us-east.pmpmining.com:5085"]
      },
      {
        "geo": "USA (St Louis) Lo Diff",
        "urls": ["us-central.pmpmining.com:5084"]
      },
      {
        "geo": "USA (St Louis) Hi Diff",
        "urls": ["us-central.pmpmining.com:5085"]
      },
      {
        "geo": "ASIA (Singapore) Lo Diff",
        "urls": ["sg.pmpmining.com:5084"]
      },
      {
        "geo": "ASIA (Singapore) Hi Diff",
        "urls": ["sg.pmpmining.com:5085"]
      }
    ],
    "miners": {
      "srbminer": {
        "url": "%URL%",
        "algo": "sha256dt",
        "pass": "x",
        "worker": "%WORKER_NAME%",
        "template": "%WAL%",
        "user_config": "--disable-cpu"
      },
      "bzminer": {
        "url": "stratum+tcp://%URL%",
        "algo": "novo",
        "pass": "x",
        "worker": "%WORKER_NAME%",
        "template": "%WAL%"
      }
    }
  },
  {
    "coin": "OBTC",
    "servers": [
      {
        "geo": "Australia (Sydney) Lo Diff",
        "urls": ["au.pmpmining.com:3072"]
      },
      {
        "geo": "Australia (Sydney) Hi Diff",
        "urls": ["au.pmpmining.com:3073"]
      },
      {
        "geo": "Sth America (Brasil / Sao Paulo) Lo Diff",
        "urls": ["br.pmpmining.com:3072"]
      },
      {
        "geo": "Sth America (Brasil / Sao Paulo) Hi Diff",
        "urls": ["br.pmpmining.com:3073"]
      },
      {
        "geo": "Europe (Germany / Dusseldorf) Lo Diff",
        "urls": ["de.pmpmining.com:3072"]
      },
      {
        "geo": "Europe (Germany / Dusseldorf) Hi Diff",
        "urls": ["de.pmpmining.com:3073"]
      },
      {
        "geo": "USA (South Carolina) Lo Diff",
        "urls": ["us-east.pmpmining.com:3072"]
      },
      {
        "geo": "USA (South Carolina) Hi Diff",
        "urls": ["us-east.pmpmining.com:3073"]
      },
      {
        "geo": "USA (St Louis) Lo Diff",
        "urls": ["us-central.pmpmining.com:3072"]
      },
      {
        "geo": "USA (St Louis) Hi Diff",
        "urls": ["us-central.pmpmining.com:3073"]
      },
      {
        "geo": "ASIA (Singapore) Lo Diff",
        "urls": ["sg.pmpmining.com:3072"]
      },
      {
        "geo": "ASIA (Singapore) Hi Diff",
        "urls": ["sg.pmpmining.com:3073"]
      }
    ],
    "miners": {
      "wildrig-multi": {
        "url": "%URL%",
        "algo": "heavyhash",
        "pass": "x",
        "template": "%WAL%.%WORKER_NAME%"
      }
    }
  },
  {
    "coin": "PAPRY",
    "servers": [
      {
        "geo": "Australia (Sydney)",
        "urls": ["au.pmpmining.com:9186"]
      },
      {
        "geo": "Sth America (Brasil / Sao Paulo)",
        "urls": ["br.pmpmining.com:9186"]
      },
      {
        "geo": "Europe (Germany / Dusseldorf)",
        "urls": ["de.pmpmining.com:9186"]
      },
      {
        "geo": "USA (South Carolina)",
        "urls": ["us-east.pmpmining.com:9186"]
      },
      {
        "geo": "USA (St Louis)",
        "urls": ["us-central.pmpmining.com:9186"]
      },
      {
        "geo": "ASIA (Singapore)",
        "urls": ["sg.pmpmining.com:9186"]
      }
    ],
    "miners": {
      "_prototype": "miners_kawpow"
    }
  },
  {
    "coin": "QOGE",
    "servers": [
      {
        "geo": "Australia (Sydney)",
        "urls": ["au.pmpmining.com:5089"]
      },
      {
        "geo": "Sth America (Brasil / Sao Paulo)",
        "urls": ["br.pmpmining.com:5089"]
      },
      {
        "geo": "Europe (Germany / Dusseldorf)",
        "urls": ["de.pmpmining.com:5089"]
      },
      {
        "geo": "USA (South Carolina)",
        "urls": ["us-east.pmpmining.com:5089"]
      },
      {
        "geo": "USA (St Louis)",
        "urls": ["us-central.pmpmining.com:5089"]
      },
      {
        "geo": "ASIA (Singapore)",
        "urls": ["sg.pmpmining.com:5089"]
      }
    ],
    "miners": {
      "srbminer": {
        "url": "%URL%",
        "algo": "yescryptr16",
        "pass": "x",
        "worker": "%WORKER_NAME%",
        "template": "%WAL%",
        "user_config": "--disable-cpu"
      }
    }
  },
  {
    "coin": "RXD",
    "servers": [
      {
        "geo": "Australia (Sydney) Lo Diff",
        "urls": ["au.pmpmining.com:3082"]
      },
      {
        "geo": "Australia (Sydney) Hi Diff",
        "urls": ["au.pmpmining.com:3083"]
      },
      {
        "geo": "Sth America (Brasil / Sao Paulo) Lo Diff",
        "urls": ["br.pmpmining.com:3082"]
      },
      {
        "geo": "Sth America (Brasil / Sao Paulo) Hi Diff",
        "urls": ["br.pmpmining.com:3083"]
      },
      {
        "geo": "Europe (Germany / Dusseldorf) Lo Diff",
        "urls": ["de.pmpmining.com:3082"]
      },
      {
        "geo": "Europe (Germany / Dusseldorf) Hi Diff",
        "urls": ["de.pmpmining.com:3083"]
      },
      {
        "geo": "USA (South Carolina) Lo Diff",
        "urls": ["us-east.pmpmining.com:3082"]
      },
      {
        "geo": "USA (South Carolina) Hi Diff",
        "urls": ["us-east.pmpmining.com:3083"]
      },
      {
        "geo": "USA (St Louis) Lo Diff",
        "urls": ["us-central.pmpmining.com:3082"]
      },
      {
        "geo": "USA (St Louis) Hi Diff",
        "urls": ["us-central.pmpmining.com:3083"]
      },
      {
        "geo": "ASIA (Singapore) Lo Diff",
        "urls": ["sg.pmpmining.com:3082"]
      },
      {
        "geo": "ASIA (Singapore) Hi Diff",
        "urls": ["sg.pmpmining.com:3083"]
      }
    ],
    "miners": {
      "_prototype": "miners_radiant"
    }
  },
  {
    "coin": "RTM",
    "servers": [
      {
        "geo": "Australia (Sydney)",
        "urls": ["au.pmpmining.com:5012"]
      },
      {
        "geo": "Sth America (Brasil / Sao Paulo)",
        "urls": ["br.pmpmining.com:5012"]
      },
      {
        "geo": "Europe (Germany / Dusseldorf)",
        "urls": ["de.pmpmining.com:5012"]
      },
      {
        "geo": "USA (South Carolina)",
        "urls": ["us-east.pmpmining.com:5012"]
      },
      {
        "geo": "USA (St Louis)",
        "urls": ["us-central.pmpmining.com:5012"]
      },
      {
        "geo": "ASIA (Singapore)",
        "urls": ["sg.pmpmining.com:5012"]
      }
    ],
    "miners": {
      "_prototype": "miners_ghostrider"
    }
  },
  {
    "coin": "YERB",
    "servers": [
      {
        "geo": "Australia (Sydney)",
        "urls": ["au.pmpmining.com:5035"]
      },
      {
        "geo": "Sth America (Brasil / Sao Paulo)",
        "urls": ["br.pmpmining.com:5035"]
      },
      {
        "geo": "Europe (Germany / Dusseldorf)",
        "urls": ["de.pmpmining.com:5035"]
      },
      {
        "geo": "USA (South Carolina)",
        "urls": ["us-east.pmpmining.com:5035"]
      },
      {
        "geo": "USA (St Louis)",
        "urls": ["us-central.pmpmining.com:5035"]
      },
      {
        "geo": "ASIA (Singapore)",
        "urls": ["sg.pmpmining.com:5035"]
      }
    ],
    "miners": {
      "_prototype": "miners_ghostrider"
    }
  }
]
