[
  {
    "pool": {
      "name": "Pools4mining.com",
      "url": "https://pools4mining.com",
      "type": "SOLO"
    }
  },

  {
    "coin": "HTN",
    "servers": [
      {
         "geo": "EU",
         "urls": [
             "eu.pools4mining.com:2211"
         ]
      },
      {
         "geo": "ASIA",
         "urls": [
             "asia-sg.pools4mining.com:2211"
        ]
      },
      {
        "geo": "US",
        "urls": [
             "us.pools4mining.com:2211"
        ]
      }
    ],
    "miners": {
         "_prototype": "miners_hoohash"
    }
  },

  {
    "coin": "PUG",
    "servers": [
      {
        "geo": "EU",
        "urls": [
          "eu.pools4mining.com:2231"
        ]
      },
      {
        "geo": "ASIA",
        "urls": [
          "asia-sg.pools4mining.com:2231"
        ]
      },
      {
        "geo": "US",
        "urls": [
          "us.pools4mining.com:2231"
        ]
      }
    ],
    "miners": {
      "rigel": {
        "url": "%URL%",
        "algo": "KARLSEN",
        "pass": "x",
        "template": "%WAL%.%WORKER_NAME%"
      },
      "lolminer": {
        "algo": "KARLSEN",
        "pass": "x",
        "port": "%URL_PORT%",
        "server": "%URL_HOST%",
        "template": "%WAL%.%WORKER_NAME%"
      },
      "nanominer": {
        "url": "%URL%",
        "algo": "karlsenhash",
        "template": "%WAL%.%WORKER_NAME%"
      },
      "miniz": {
      "algo": "karlsen",
      "url": "%URL%",
      "pass": "x",
      "template": "%WAL%.%WORKER_NAME%",
      "user_config": "--pers auto"
      }
    }
  },
  {
    "coin": "KODA",
    "servers": [
      {
        "geo": "EU",
        "urls": [
          "eu.pools4mining.com:2241"
        ]
      },
      {
        "geo": "ASIA",
        "urls": [
          "asia-sg.pools4mining.com:2241"
        ]
      },
      {
        "geo": "US",
        "urls": [
          "us.pools4mining.com:2241"
        ]
      }
    ],
    "miners": {
      "rigel": {
        "url": "%URL%",
        "algo": "pyrinhash",
        "pass": "x",
        "template": "%WAL%.%WORKER_NAME%"
      },
      "lolminer": {
        "algo": "PYRIN",
        "pass": "x",
        "port": "%URL_PORT%",
        "server": "%URL_HOST%",
        "template": "%WAL%.%WORKER_NAME%"
      },
      "nanominer": {
        "url": "%URL%",
        "algo": "pyrinhash",
        "template": "%WAL%.%WORKER_NAME%"
      },
      "miniz": {
      "algo": "pyrin",
      "url": "%URL%",
      "pass": "x",
      "template": "%WAL%.%WORKER_NAME%",
      "user_config": "--pers auto"
      }
    }
  },

  {
    "coin": "PYI",
    "servers": [
      {
        "geo": "EU",
        "urls": [
          "eu.pools4mining.com:2221"
        ]
      },
      {
        "geo": "ASIA",
        "urls": [
          "asia-sg.pools4mining.com:2221"
        ]
      },
      {
        "geo": "US",
        "urls": [
          "us.pools4mining.com:2221"
        ]
      }
    ],
    "miners": {
      "rigel": {
        "url": "%URL%",
        "algo": "pyrinhash",
        "pass": "x",
        "template": "%WAL%.%WORKER_NAME%"
      },
      "lolminer": {
        "algo": "PYRIN",
        "pass": "x",
        "port": "%URL_PORT%",
        "server": "%URL_HOST%",
        "template": "%WAL%.%WORKER_NAME%"
      },
      "nanominer": {
        "url": "%URL%",
        "algo": "pyrinhash",
        "template": "%WAL%.%WORKER_NAME%"
      },
      "miniz": {
      "algo": "pyrin",
      "url": "%URL%",
      "pass": "x",
      "template": "%WAL%.%WORKER_NAME%",
      "user_config": "--pers auto"
      }
    }
  }
]
