[
    {
        "coin": "AKA",
        "servers": [
            {
                "geo": null,
                "urls": [
                    "aka.pool.sexy:20022"
                ]
            }
        ],
        "miners": {
            "claymore": {
                "epools_tpl": "POOL: %URL%, WALLET: %WAL%, WORKER: %WORKER_NAME%, PSW: x, ALLPOOLS: 1"
            },
            "ethminer": {
                "cuda": 1,
                "pass": "x",
                "port": "%URL_PORT%",
                "server": "stratum1+tcp://%URL_HOST%",
                "template": "%WAL%.%WORKER_NAME%",
                "user_config": "--farm-recheck 2000"
            },
			 "asicminer": {
                "url": "stratum+tcp://%URL%",
                "template": "%WAL%.%WORKER_NAME%"
            }
        }
    },
    {
        "coin": "CLO",
        "servers": [
            {
                "geo": null,
                "urls": [
                    "clo.pool.sexy:20052"
                ]
            }
        ],
        "miners": {
            "claymore": {
                "epools_tpl": "POOL: %URL%, WALLET: %WAL%, WORKER: %WORKER_NAME%, PSW: x, ALLPOOLS: 1"
            },
            "ethminer": {
                "cuda": 1,
                "pass": "x",
                "port": "%URL_PORT%",
                "server": "stratum1+tcp://%URL_HOST%",
                "template": "%WAL%.%WORKER_NAME%",
                "user_config": "--farm-recheck 2000"
            },
			 "asicminer": {
                "url": "stratum+tcp://%URL%",
                "template": "%WAL%.%WORKER_NAME%"
            }
        }
    },
    {
        "coin": "DBIX",
        "servers": [
            {
                "geo": null,
                "urls": [
                    "dbix.pool.sexy:10032"
                ]
            }
        ],
        "miners": {
            "claymore": {
                "epools_tpl": "POOL: %URL%, WALLET: %WAL%, WORKER: %WORKER_NAME%, PSW: x, ALLPOOLS: 1"
            },
            "ethminer": {
                "cuda": 1,
                "pass": "x",
                "port": "%URL_PORT%",
                "server": "stratum1+tcp://%URL_HOST%",
                "template": "%WAL%.%WORKER_NAME%",
                "user_config": "--farm-recheck 2000"
            },
			 "asicminer": {
                "url": "stratum+tcp://%URL%",
                "template": "%WAL%.%WORKER_NAME%"
            }
        }
    },
    {
        "coin": "ELLA",
        "servers": [
            {
                "geo": null,
                "urls": [
                    "ella.pool.sexy:10082"
                ]
            }
        ],
        "miners": {
            "claymore": {
                "epools_tpl": "POOL: %URL%, WALLET: %WAL%, WORKER: %WORKER_NAME%, PSW: x, ALLPOOLS: 1"
            },
            "ethminer": {
                "cuda": 1,
                "pass": "x",
                "port": "%URL_PORT%",
                "server": "stratum1+tcp://%URL_HOST%",
                "template": "%WAL%.%WORKER_NAME%",
                "user_config": "--farm-recheck 2000"
            },
			 "asicminer": {
                "url": "stratum+tcp://%URL%",
                "template": "%WAL%.%WORKER_NAME%"
            }
        }
    },
    {
        "coin": "ETHO",
        "servers": [
            {
                "geo": null,
                "urls": [
                    "etho.pool.sexy:20032"
                ]
            }
        ],
        "miners": {
            "claymore": {
                "epools_tpl": "POOL: %URL%, WALLET: %WAL%, WORKER: %WORKER_NAME%, PSW: x, ALLPOOLS: 1"
            },
            "ethminer": {
                "cuda": 1,
                "pass": "x",
                "port": "%URL_PORT%",
                "server": "stratum1+tcp://%URL_HOST%",
                "template": "%WAL%.%WORKER_NAME%",
                "user_config": "--farm-recheck 2000"
            },
			 "asicminer": {
                "url": "stratum+tcp://%URL%",
                "template": "%WAL%.%WORKER_NAME%"
            }
        }
    },
    {
        "coin": "MUSIC",
        "servers": [
            {
                "geo": null,
                "urls": [
                    "music.pool.sexy:10012"
                ]
            }
        ],
        "miners": {
            "claymore": {
                "epools_tpl": "POOL: %URL%, WALLET: %WAL%, WORKER: %WORKER_NAME%, PSW: x, ALLPOOLS: 1"
            },
            "ethminer": {
                "cuda": 1,
                "pass": "x",
                "port": "%URL_PORT%",
                "server": "stratum1+tcp://%URL_HOST%",
                "template": "%WAL%.%WORKER_NAME%",
                "user_config": "--farm-recheck 2000"
            },
			 "asicminer": {
                "url": "stratum+tcp://%URL%",
                "template": "%WAL%.%WORKER_NAME%"
            }
        }
    },
    {
        "coin": "PIRL",
        "servers": [
            {
                "geo": null,
                "urls": [
                    "pirl.pool.sexy:10052"
                ]
            }
        ],
        "miners": {
            "claymore": {
                "epools_tpl": "POOL: %URL%, WALLET: %WAL%, WORKER: %WORKER_NAME%, PSW: x, ALLPOOLS: 1"
            },
            "ethminer": {
                "cuda": 1,
                "pass": "x",
                "port": "%URL_PORT%",
                "server": "stratum1+tcp://%URL_HOST%",
                "template": "%WAL%.%WORKER_NAME%",
                "user_config": "--farm-recheck 2000"
            },
			 "asicminer": {
                "url": "stratum+tcp://%URL%",
                "template": "%WAL%.%WORKER_NAME%"
            }
        }
    },
    {
        "coin": "GOL",
        "servers": [
            {
                "geo": null,
                "urls": [
                    "gol.pool.sexy:20012"
                ]
            }
        ],
        "miners": {
            "claymore": {
                "epools_tpl": "POOL: %URL%, WALLET: %WAL%, WORKER: %WORKER_NAME%, PSW: x, ALLPOOLS: 1"
            },
            "ethminer": {
                "cuda": 1,
                "pass": "x",
                "port": "%URL_PORT%",
                "server": "stratum1+tcp://%URL_HOST%",
                "template": "%WAL%.%WORKER_NAME%",
                "user_config": "--farm-recheck 2000"
            },
			 "asicminer": {
                "url": "stratum+tcp://%URL%",
                "template": "%WAL%.%WORKER_NAME%"
            }
        }
    },
    {
        "coin": "UBQ",
        "servers": [
            {
                "geo": null,
                "urls": [
                    "ubq.pool.sexy:20042"
                ]
            }
        ],
        "miners": {
            "claymore": {
                "epools_tpl": "POOL: %URL%, WALLET: %WAL%, WORKER: %WORKER_NAME%, PSW: x, ALLPOOLS: 1"
            },
            "ethminer": {
                "cuda": 1,
                "pass": "x",
                "port": "%URL_PORT%",
                "server": "stratum1+tcp://%URL_HOST%",
                "template": "%WAL%.%WORKER_NAME%",
                "user_config": "--farm-recheck 2000"
            },
			 "asicminer": {
                "url": "stratum+tcp://%URL%",
                "template": "%WAL%.%WORKER_NAME%"
            }
        }
    },
    {
        "coin": "MOAC",
        "servers": [
            {
                "geo": null,
                "urls": [
                    "moac.pool.sexy:10092"
                ]
            }
        ],
        "miners": {
            "claymore": {
                "epools_tpl": "POOL: %URL%, WALLET: %WAL%, WORKER: %WORKER_NAME%, PSW: x, ALLPOOLS: 1"
            },
            "ethminer": {
                "cuda": 1,
                "pass": "x",
                "port": "%URL_PORT%",
                "server": "stratum1+tcp://%URL_HOST%",
                "template": "%WAL%.%WORKER_NAME%",
                "user_config": "--farm-recheck 2000"
            },
			 "asicminer": {
                "url": "stratum+tcp://%URL%",
                "template": "%WAL%.%WORKER_NAME%"
            }
        }
    }
]
